SimpleTimedLogger/SimpleTimedLogger.py
SimpleTimedLogger/__init__.py
simpletimedlogger-2.0.2.dist-info/METADATA
simpletimedlogger-2.0.2.dist-info/WHEEL
simpletimedlogger-2.0.2.dist-info/licenses/LICENSE
simpletimedlogger-2.0.2.dist-info/RECORD
