Metadata-Version: 2.1
Name: SimpleTimedLogger
Version: 2.0.2
Summary: Simple Timed logger, it write logs to terminal. Can write elapsed time between logs
Project-URL: Homepage, https://gitlab.com/Almex/simpletimedlogger
Project-URL: Bug Tracker, https://gitlab.com/Almex/simpletimedlogger/-/issues
Author-email: Karolis Andriunas <almex.developer@gmail.com>
License-File: LICENSE
Classifier: Intended Audience :: Developers
Classifier: License :: OSI Approved :: GNU General Public License v3 or later (GPLv3+)
Classifier: Operating System :: OS Independent
Classifier: Programming Language :: Python :: 3
Requires-Python: >=3.7
